README
setup.py
scikits/__init__.py
scikits.scattpy.egg-info/PKG-INFO
scikits.scattpy.egg-info/SOURCES.txt
scikits.scattpy.egg-info/dependency_links.txt
scikits.scattpy.egg-info/namespace_packages.txt
scikits.scattpy.egg-info/requires.txt
scikits.scattpy.egg-info/top_level.txt
scikits.scattpy.egg-info/zip-safe
scikits/scattpy/__init__.py
scikits/scattpy/core.py
scikits/scattpy/doc_inherit.py
scikits/scattpy/laboratory.py
scikits/scattpy/methods.py
scikits/scattpy/spherical.py
scikits/scattpy/version.py
src/f_utils.for