Metadata-Version: 1.0
Name: scikits.scattpy
Version: 0.1.0
Summary: Light Scattering methods for Python
Home-page: http://scattpy.github.com
Author: ('Alexander Vinokurov',)
Author-email: ('scattpy@googlegroups.com',)
License: BSD
Download-URL: http://github.com/downloads/ScattPy/scikits.scattpy/scikits.scattpy-0.1.0.tar.gz
Platform: UNKNOWN
Classifier: Development Status :: 4 - Beta
Classifier: Environment :: Console
Classifier: Intended Audience :: Developers
Classifier: Intended Audience :: Science/Research
Classifier: Intended Audience :: Education
Classifier: License :: OSI Approved :: BSD License
Classifier: Topic :: Scientific/Engineering :: Mathematics
Classifier: Topic :: Scientific/Engineering :: Physics
Classifier: Topic :: Scientific/Engineering :: Astronomy
